focusedme/Ring01.wav
focusedme/__init__.py
focusedme/__main__.py
focusedme/util.py
focusedme-0.1.84.dist-info/AUTHORS.rst
focusedme-0.1.84.dist-info/LICENSE
focusedme-0.1.84.dist-info/METADATA
focusedme-0.1.84.dist-info/WHEEL
focusedme-0.1.84.dist-info/entry_points.txt
focusedme-0.1.84.dist-info/RECORD
