Metadata-Version: 2.3
Name: focusedme
Version: 0.1.84
Summary: A minimalist Pomodoro timer that runs in your terminal
License: MIT
Keywords: pomodoro,timer,productivity,terminal,cli
Author: Fabio Scopeta
Author-email: scopeta@gmail.com
Requires-Python: >=3.9,<4.0
Classifier: Development Status :: 4 - Beta
Classifier: Environment :: Console
Classifier: Intended Audience :: Developers
Classifier: License :: OSI Approved :: MIT License
Classifier: Natural Language :: English
Classifier: Operating System :: OS Independent
Classifier: Programming Language :: Python :: 3
Classifier: Programming Language :: Python :: 3.9
Classifier: Programming Language :: Python :: 3.10
Classifier: Programming Language :: Python :: 3.11
Classifier: Programming Language :: Python :: 3.12
Classifier: Programming Language :: Python :: 3.13
Classifier: Topic :: Office/Business
Classifier: Topic :: Utilities
Requires-Dist: rich (>=13.5.0,<14.0.0)
Requires-Dist: simpleaudio (>=1.0.4,<2.0.0) ; sys_platform != "darwin" and sys_platform != "win32"
Project-URL: Documentation, https://scopeta.github.io/focusedme/
Project-URL: Homepage, https://github.com/scopeta/focusedme
Project-URL: Repository, https://github.com/scopeta/focusedme
